<HighSchoolTimetableArchive Id="./datos/informatica_le.csv"><Instances><Instance Id="./datos/informatica_le.csv"><MetaData><Name>Horario de Informatica</Name><Contributor>Jose Ramon Vejo</Contributor><Date>2017-03-21 17:12:03.043428</Date><Country>Spain</Country><Description>Unican</Description></MetaData><Times><TimeGroups><Day Id="Lunes"><Name>Lunes</Name></Day><Day Id="Martes"><Name>Martes</Name></Day><Day Id="Miercoles"><Name>Miercoles</Name></Day><TimeGroup Id="TodasHoras"><Name>Todas horas</Name></TimeGroup><TimeGroup Id="AntesDescanso"><Name>AntesDescanso</Name></TimeGroup><TimeGroup Id="DespuesDescanso"><Name>DespuesDescanso</Name></TimeGroup><TimeGroup Id="Tarde"><Name>Tarde</Name></TimeGroup></TimeGroups><Time Id="Lunes1"><Name>Lunes - 1</Name><Day Reference="Lunes" /><TimeGroups><TimeGroup Reference="AntesDescanso" /><TimeGroup Reference="TodasHoras" /></TimeGroups></Time><Time Id="Martes1"><Name>Martes - 1</Name><Day Reference="Martes" /><TimeGroups><TimeGroup Reference="AntesDescanso" /><TimeGroup Reference="TodasHoras" /></TimeGroups></Time><Time Id="Miercoles1"><Name>Miercoles - 1</Name><Day Reference="Miercoles" /><TimeGroups><TimeGroup Reference="AntesDescanso" /><TimeGroup Reference="TodasHoras" /></TimeGroups></Time><Time Id="Lunes2"><Name>Lunes - 2</Name><Day Reference="Lunes" /><TimeGroups><TimeGroup Reference="AntesDescanso" /><TimeGroup Reference="TodasHoras" /></TimeGroups></Time><Time Id="Martes2"><Name>Martes - 2</Name><Day Reference="Martes" /><TimeGroups><TimeGroup Reference="AntesDescanso" /><TimeGroup Reference="TodasHoras" /></TimeGroups></Time><Time Id="Miercoles2"><Name>Miercoles - 2</Name><Day Reference="Miercoles" /><TimeGroups><TimeGroup Reference="AntesDescanso" /><TimeGroup Reference="TodasHoras" /></TimeGroups></Time></Times><Resources><ResourceTypes><ResourceType Id="Profesores"><Name>Profesores</Name></ResourceType><ResourceType Id="Aulas"><Name>Aulas</Name></ResourceType><ResourceType Id="Cursos"><Name>Cursos</Name></ResourceType><ResourceType Id="Cuatrimestres"><Name>Cuatrimestres</Name></ResourceType></ResourceTypes><ResourceGroups><ResourceGroup Id="gr_Profesores"><Name>Profesores</Name><ResourceType Reference="Profesores" /></ResourceGroup><ResourceGroup Id="gr_Aulas"><Name>Aulas</Name><ResourceType Reference="Aulas" /></ResourceGroup><ResourceGroup Id="gr_Cursos"><Name>Cursos</Name><ResourceType Reference="Cursos" /></ResourceGroup><ResourceGroup Id="gr_Cuatrimestres"><Name>Cuatrimestres</Name><ResourceType Reference="Cuatrimestres" /></ResourceGroup><ResourceGroup Id="Grandes"><Name>Cuatrimestres</Name><ResourceType Reference="Aulas" /></ResourceGroup><ResourceGroup Id="Normales"><Name>Cuatrimestres</Name><ResourceType Reference="Aulas" /></ResourceGroup><ResourceGroup Id="Laboratorios"><Name>Cuatrimestres</Name><ResourceType Reference="Aulas" /></ResourceGroup><ResourceGroup Id="Pequenas"><Name>Cuatrimestres</Name><ResourceType Reference="Aulas" /></ResourceGroup><ResourceGroup Id="Curso_11"><Name>Curso_11</Name><ResourceType Reference="Cursos" /></ResourceGroup><ResourceGroup Id="Curso_12"><Name>Curso_12</Name><ResourceType Reference="Cursos" /></ResourceGroup><ResourceGroup Id="Curso_21"><Name>Curso_21</Name><ResourceType Reference="Cursos" /></ResourceGroup><ResourceGroup Id="Curso_22"><Name>Curso_22</Name><ResourceType Reference="Cursos" /></ResourceGroup><ResourceGroup Id="Curso_31"><Name>Curso_31</Name><ResourceType Reference="Cursos" /></ResourceGroup><ResourceGroup Id="Curso_32"><Name>Curso_32</Name><ResourceType Reference="Cursos" /></ResourceGroup><ResourceGroup Id="Curso_41"><Name>Curso_41</Name><ResourceType Reference="Cursos" /></ResourceGroup><ResourceGroup Id="Curso_42"><Name>Curso_42</Name><ResourceType Reference="Cursos" /></ResourceGroup><ResourceGroup Id="Cuatrimestre_1"><Name>Cuatrimestre_1</Name><ResourceType Reference="Cuatrimestres" /></ResourceGroup><ResourceGroup Id="Cuatrimestre_2"><Name>Cuatrimestre_2</Name><ResourceType Reference="Cuatrimestres" /></ResourceGroup></ResourceGroups><Resource Id="JOSE_MARIA_SENTIES_VIAN"><Name>JOSE MARIA SENTIES VIAN</Name><ResourceType Reference="Profesores" /><ResourceGroups><ResourceGroup Reference="gr_Profesores" /></ResourceGroups></Resource><Resource Id="JOSE_ANGEL_GREGORIO_MONASTERIO"><Name>JOSE ANGEL GREGORIO MONASTERIO</Name><ResourceType Reference="Profesores" /><ResourceGroups><ResourceGroup Reference="gr_Profesores" /></ResourceGroups></Resource><Resource Id="ALFONSO_DE_LA_VEGA_RUIZ"><Name>ALFONSO DE LA VEGA RUIZ</Name><ResourceType Reference="Profesores" /><ResourceGroups><ResourceGroup Reference="gr_Profesores" /></ResourceGroups></Resource><Resource Id="PABLO_PRIETO_TORRALBO"><Name>PABLO PRIETO TORRALBO</Name><ResourceType Reference="Profesores" /><ResourceGroups><ResourceGroup Reference="gr_Profesores" /></ResourceGroups></Resource><Resource Id="JUAN_ANTONIO_SAIZ_IPI&#209;A"><Name>JUAN ANTONIO SAIZ IPI&#209;A</Name><ResourceType Reference="Profesores" /><ResourceGroups><ResourceGroup Reference="gr_Profesores" /></ResourceGroups></Resource><Resource Id="ALEJANDRO_PEREZ_RUIZ"><Name>ALEJANDRO PEREZ RUIZ</Name><ResourceType Reference="Profesores" /><ResourceGroups><ResourceGroup Reference="gr_Profesores" /></ResourceGroups></Resource><Resource Id="JOSE_CARLOS_PALENCIA_GUTIERREZ"><Name>JOSE CARLOS PALENCIA GUTIERREZ</Name><ResourceType Reference="Profesores" /><ResourceGroups><ResourceGroup Reference="gr_Profesores" /></ResourceGroups></Resource><Resource Id="MICHAEL_GONZALEZ_HARBOUR"><Name>MICHAEL GONZALEZ HARBOUR</Name><ResourceType Reference="Profesores" /><ResourceGroups><ResourceGroup Reference="gr_Profesores" /></ResourceGroups></Resource><Resource Id="ANDRES_PRIETO_GALA"><Name>ANDRES PRIETO GALA</Name><ResourceType Reference="Profesores" /><ResourceGroups><ResourceGroup Reference="gr_Profesores" /></ResourceGroups></Resource><Resource Id="ANGEL_VEGAS_GARCIA"><Name>ANGEL VEGAS GARCIA</Name><ResourceType Reference="Profesores" /><ResourceGroups><ResourceGroup Reference="gr_Profesores" /></ResourceGroups></Resource><Resource Id="ADOLFO_GARANDAL_MARTIN"><Name>ADOLFO GARANDAL MARTIN</Name><ResourceType Reference="Profesores" /><ResourceGroups><ResourceGroup Reference="gr_Profesores" /></ResourceGroups></Resource><Resource Id="Aula 12"><Name>Aula 12</Name><ResourceType Reference="Aulas" /><ResourceGroups><ResourceGroup Reference="Pequenas" /><ResourceGroup Reference="gr_Aulas" /></ResourceGroups></Resource><Resource Id="Aula 2"><Name>Aula 2</Name><ResourceType Reference="Aulas" /><ResourceGroups><ResourceGroup Reference="Grandes" /><ResourceGroup Reference="gr_Aulas" /></ResourceGroups></Resource><Resource Id="Aula 1"><Name>Aula 1</Name><ResourceType Reference="Aulas" /><ResourceGroups><ResourceGroup Reference="Grandes" /><ResourceGroup Reference="gr_Aulas" /></ResourceGroups></Resource><Resource Id="Lab 1"><Name>Lab 1</Name><ResourceType Reference="Aulas" /><ResourceGroups><ResourceGroup Reference="Normales" /><ResourceGroup Reference="gr_Aulas" /><ResourceGroup Reference="Laboratorios" /></ResourceGroups></Resource><Resource Id="Curso_11"><Name>Curso_11</Name><ResourceType Reference="Cursos" /><ResourceGroups><ResourceGroup Reference="gr_Cursos" /></ResourceGroups></Resource><Resource Id="Curso_12"><Name>Curso_12</Name><ResourceType Reference="Cursos" /><ResourceGroups><ResourceGroup Reference="gr_Cursos" /></ResourceGroups></Resource><Resource Id="Curso_21"><Name>Curso_21</Name><ResourceType Reference="Cursos" /><ResourceGroups><ResourceGroup Reference="gr_Cursos" /></ResourceGroups></Resource><Resource Id="Curso_22"><Name>Curso_22</Name><ResourceType Reference="Cursos" /><ResourceGroups><ResourceGroup Reference="gr_Cursos" /></ResourceGroups></Resource><Resource Id="Curso_31"><Name>Curso_31</Name><ResourceType Reference="Cursos" /><ResourceGroups><ResourceGroup Reference="gr_Cursos" /></ResourceGroups></Resource><Resource Id="Curso_32"><Name>Curso_32</Name><ResourceType Reference="Cursos" /><ResourceGroups><ResourceGroup Reference="gr_Cursos" /></ResourceGroups></Resource><Resource Id="Curso_41"><Name>Curso_41</Name><ResourceType Reference="Cursos" /><ResourceGroups><ResourceGroup Reference="gr_Cursos" /></ResourceGroups></Resource><Resource Id="Curso_42"><Name>Curso_42</Name><ResourceType Reference="Cursos" /><ResourceGroups><ResourceGroup Reference="gr_Cursos" /></ResourceGroups></Resource></Resources><Events><Event Id="&#193;lgebra Lineal y Discreta_t"><Name>&#193;lgebra Lineal y Discreta: Teoria</Name><Duration>5</Duration><Resources><Resource Reference="Curso_11" /><Resource Reference="Curso_12" /></Resources></Event><Event Id="Introducci&#243;n al Software_t"><Name>Introducci&#243;n al Software: Teoria</Name><Duration>4</Duration><Resources><Resource Reference="Curso_11" /><Resource Reference="Curso_12" /><Resource Reference="ALFONSO_DE_LA_VEGA_RUIZ" /><Resource Reference="ALEJANDRO_PEREZ_RUIZ" /><Resource Reference="JOSE_CARLOS_PALENCIA_GUTIERREZ" /><Resource Reference="MICHAEL_GONZALEZ_HARBOUR" /></Resources></Event><Event Id="Sistemas Digitales_t"><Name>Sistemas Digitales: Teoria</Name><Duration>2</Duration><Resources><Resource Reference="Curso_11" /><Resource Reference="Curso_12" /></Resources></Event><Event Id="Fundamentos F&#237;sicos de la Inform&#225;tica_t"><Name>Fundamentos F&#237;sicos de la Inform&#225;tica: Teoria</Name><Duration>6</Duration><Resources><Resource Reference="Curso_11" /><Resource Reference="Curso_12" /><Resource Reference="JOSE_MARIA_SENTIES_VIAN" /><Resource Reference="JUAN_ANTONIO_SAIZ_IPI&#209;A" /><Resource Reference="ANDRES_PRIETO_GALA" /><Resource Reference="ANGEL_VEGAS_GARCIA" /></Resources></Event></Events><Constraints><AvoidClashesConstraint Id="Choques"><Name>Choques</Name><Required>true</Required><Weight>1</Weight><CostFunction>Linear</CostFunction><AppliesTo><ResourceGroups><ResourceGroup Reference="gr_Profesores" /><ResourceGroup Reference="gr_Aulas" /><ResourceGroup Reference="gr_Cursos" /><ResourceGroup Reference="gr_Cuatrimestres" /></ResourceGroups></AppliesTo></AvoidClashesConstraint></Constraints></Instance></Instances></HighSchoolTimetableArchive>